odoo8_addon_medical_insurance-8.0.1.1.0.99.dev6-py2.7-nspkg.pth
odoo8_addon_medical_insurance-8.0.1.1.0.99.dev6.dist-info/DESCRIPTION.rst
odoo8_addon_medical_insurance-8.0.1.1.0.99.dev6.dist-info/METADATA
odoo8_addon_medical_insurance-8.0.1.1.0.99.dev6.dist-info/RECORD
odoo8_addon_medical_insurance-8.0.1.1.0.99.dev6.dist-info/WHEEL
odoo8_addon_medical_insurance-8.0.1.1.0.99.dev6.dist-info/metadata.json
odoo8_addon_medical_insurance-8.0.1.1.0.99.dev6.dist-info/namespace_packages.txt
odoo8_addon_medical_insurance-8.0.1.1.0.99.dev6.dist-info/top_level.txt
odoo_addons/medical_insurance/README.rst
odoo_addons/medical_insurance/__init__.py
odoo_addons/medical_insurance/__openerp__.py
odoo_addons/medical_insurance/i18n/pt_BR.po
odoo_addons/medical_insurance/i18n/sl.po
odoo_addons/medical_insurance/models/__init__.py
odoo_addons/medical_insurance/models/medical_insurance_company.py
odoo_addons/medical_insurance/models/medical_insurance_plan.py
odoo_addons/medical_insurance/models/medical_insurance_template.py
odoo_addons/medical_insurance/models/medical_patient.py
odoo_addons/medical_insurance/models/product_product.py
odoo_addons/medical_insurance/security/ir.model.access.csv
odoo_addons/medical_insurance/tests/__init__.py
odoo_addons/medical_insurance/tests/medical_insurance_company.yml
odoo_addons/medical_insurance/tests/medical_insurance_plan.yml
odoo_addons/medical_insurance/tests/medical_insurance_template.yml
odoo_addons/medical_insurance/tests/test_medical_insurance_company.py
odoo_addons/medical_insurance/views/medical_insurance_company_view.xml
odoo_addons/medical_insurance/views/medical_insurance_plan_view.xml
odoo_addons/medical_insurance/views/medical_insurance_template_view.xml
odoo_addons/medical_insurance/views/medical_menu.xml
odoo_addons/medical_insurance/views/medical_patient_view.xml
